"sql_organizer/__init__,.py"
sql_organizer/combiner.py
sql_organizer/file.py
sql_organizer/file_formatter.py
sql_organizer/main.py
sql_organizer/search.py
sql_organizer/sorter.py
sql_organizer-1.0.3.dist-info/METADATA
sql_organizer-1.0.3.dist-info/WHEEL
sql_organizer-1.0.3.dist-info/entry_points.txt
sql_organizer-1.0.3.dist-info/licenses/LICENSE
sql_organizer-1.0.3.dist-info/RECORD
