Metadata-Version: 2.4
Name: sql-organizer
Version: 1.0.3
Summary: This is a simple python CLI tool to organize .sql files. This is a useful tool for my work, but I decided to share it as a project example
Project-URL: Repository, https://github.com/TheSuperShell/sql-organizer
Author-email: Steven Rudenko <steven.gucum@gmail.com>
License: MIT License
License-File: LICENSE
Keywords: os,sql
Classifier: Development Status :: 4 - Beta
Classifier: Programming Language :: Python :: 3.12
Requires-Python: >=3.12
Requires-Dist: pydantic>=2.11.7
Requires-Dist: rich>=14.0.0
Requires-Dist: typer>=0.16.0
